jupyterlab_codestral/__init__.py
jupyterlab_codestral/_version.py
jupyterlab_codestral-0.1.0.data/data/share/jupyter/labextensions/jupyterlab-codestral/package.json
jupyterlab_codestral-0.1.0.data/data/share/jupyter/labextensions/jupyterlab-codestral/schemas/jupyterlab-codestral/chat.json
jupyterlab_codestral-0.1.0.data/data/share/jupyter/labextensions/jupyterlab-codestral/schemas/jupyterlab-codestral/inline-provider.json
jupyterlab_codestral-0.1.0.data/data/share/jupyter/labextensions/jupyterlab-codestral/schemas/jupyterlab-codestral/package.json.orig
jupyterlab_codestral-0.1.0.data/data/share/jupyter/labextensions/jupyterlab-codestral/static/621.48f88ec31647cc342a3f.js
jupyterlab_codestral-0.1.0.data/data/share/jupyter/labextensions/jupyterlab-codestral/static/728.bf56c4d58128fdbdc5d7.js
jupyterlab_codestral-0.1.0.data/data/share/jupyter/labextensions/jupyterlab-codestral/static/787.4f989603435ee6bcd9fe.js
jupyterlab_codestral-0.1.0.data/data/share/jupyter/labextensions/jupyterlab-codestral/static/92.24f8a07b00f83b2ffb77.js
jupyterlab_codestral-0.1.0.data/data/share/jupyter/labextensions/jupyterlab-codestral/static/960.c720a8d51cb843a8c925.js
jupyterlab_codestral-0.1.0.data/data/share/jupyter/labextensions/jupyterlab-codestral/static/960.c720a8d51cb843a8c925.js.LICENSE.txt
jupyterlab_codestral-0.1.0.data/data/share/jupyter/labextensions/jupyterlab-codestral/static/remoteEntry.07f6e8b4a9a51a35e93a.js
jupyterlab_codestral-0.1.0.data/data/share/jupyter/labextensions/jupyterlab-codestral/static/style.js
jupyterlab_codestral-0.1.0.data/data/share/jupyter/labextensions/jupyterlab-codestral/static/third-party-licenses.json
jupyterlab_codestral-0.1.0.data/data/share/jupyter/labextensions/jupyterlab-codestral/install.json
jupyterlab_codestral-0.1.0.dist-info/METADATA
jupyterlab_codestral-0.1.0.dist-info/WHEEL
jupyterlab_codestral-0.1.0.dist-info/licenses/LICENSE
jupyterlab_codestral-0.1.0.dist-info/RECORD
