Metadata-Version: 2.3
Name: jupyterlab_codestral
Version: 0.1.0
Dynamic: Keywords
Summary: Codestral AI code completions for JupyterLab
Project-URL: Homepage, https://github.com/jupyterlite/jupyterlab-codestral
Project-URL: Bug Tracker, https://github.com/jupyterlite/jupyterlab-codestral/issues
Project-URL: Repository, https://github.com/jupyterlite/jupyterlab-codestral.git
Author: Jeremy Tuloup
License: BSD 3-Clause License
License-File: LICENSE
Classifier: Framework :: Jupyter
Classifier: Framework :: Jupyter :: JupyterLab
Classifier: Framework :: Jupyter :: JupyterLab :: 4
Classifier: Framework :: Jupyter :: JupyterLab :: Extensions
Classifier: Framework :: Jupyter :: JupyterLab :: Extensions :: Prebuilt
Classifier: License :: OSI Approved :: BSD License
Classifier: Programming Language :: Python
Classifier: Programming Language :: Python :: 3
Classifier: Programming Language :: Python :: 3.8
Classifier: Programming Language :: Python :: 3.9
Classifier: Programming Language :: Python :: 3.10
Classifier: Programming Language :: Python :: 3.11
Classifier: Programming Language :: Python :: 3.12
Requires-Python: >=3.8
